sizes/__init__.py
sizes/__main__.py
sizes/_util.py
sizes/cli.py
sizes/colours.py
sizes/dir.py
sizes/file.py
sizes/utils.py
sizes_cli-0.2.1.dist-info/entry_points.txt
sizes_cli-0.2.1.dist-info/METADATA
sizes_cli-0.2.1.dist-info/WHEEL
sizes_cli-0.2.1.dist-info/RECORD
